setup.py
fasterGit/__init__.py
fasterGit/fasterGit.py
fasterGit.egg-info/PKG-INFO
fasterGit.egg-info/SOURCES.txt
fasterGit.egg-info/dependency_links.txt
fasterGit.egg-info/entry_points.txt
fasterGit.egg-info/requires.txt
fasterGit.egg-info/top_level.txt