Metadata-Version: 1.0
Name: fasterGit
Version: 0.1.2
Summary: Modify the host file to improve the speed of pulling git code
Home-page: https://github.com/WendStation/fasterGit
Author: handa
Author-email: 794363716@qq.com
License: MIT Licence
Keywords: pip,git,gitHost,host
Platform: any
